subtotal/__init__.py
subtotal/subtotal.py
subtotal-0.0.2.dist-info/METADATA
subtotal-0.0.2.dist-info/WHEEL
subtotal-0.0.2.dist-info/entry_points.txt
subtotal-0.0.2.dist-info/licenses/LICENSE.txt
subtotal-0.0.2.dist-info/RECORD
