Metadata-Version: 2.1
Name: subtotal
Version: 0.0.2
Summary: Get subdomains for a url from virustotal.com without an api key.
Project-URL: Homepage, https://github.com/matt-manes/subtotal
Project-URL: Documentation, https://github.com/matt-manes/subtotal/tree/main/docs
Project-URL: Source code, https://github.com/matt-manes/subtotal/tree/main/src/subtotal
Author-email: Matt Manes <mattmanes@pm.me>
License-File: LICENSE.txt
Keywords: automation,enumeration,subdomain
Classifier: License :: OSI Approved :: MIT License
Classifier: Operating System :: OS Independent
Classifier: Programming Language :: Python :: 3
Requires-Python: >=3.6
Requires-Dist: printbuddies
Requires-Dist: pytest
Requires-Dist: seleniumuser
